cryp/__init__.py
cryp/blockchain.py
cryp/config.py
cryp/database.py
cryp/encryption.py
cryp/main.py
cryp/scheduler.py
cryp/tool.py
cryp/webhook.py
cryp_payment-0.1.1.dist-info/METADATA
cryp_payment-0.1.1.dist-info/WHEEL
cryp_payment-0.1.1.dist-info/top_level.txt
cryp_payment-0.1.1.dist-info/RECORD
