Metadata-Version: 2.4
Name: cryp-payment
Version: 0.1.1
Summary: A cryptocurrency payment processing system for BSC
Home-page: https://github.com/wolfgang-99/cryp-payment
Author: wolfs code
Author-email: wolf's code <wolfs.code.work@gmail.com>
License: MIT
Project-URL: Homepage, https://github.com/wolfgang-99/cryp-payment
Project-URL: Documentation, https://cryp-payment.readthedocs.io
Project-URL: Repository, https://github.com/wolfgang-99/cryp-payment
Project-URL: Bug Tracker, https://github.com/wolfgang-99/cryp-payment/issues
Keywords: cryptocurrency,payment,blockchain,bsc,binance
Classifier: Development Status :: 3 - Alpha
Classifier: Intended Audience :: Developers
Classifier: License :: OSI Approved :: MIT License
Classifier: Programming Language :: Python :: 3
Classifier: Programming Language :: Python :: 3.8
Classifier: Programming Language :: Python :: 3.9
Classifier: Programming Language :: Python :: 3.10
Classifier: Programming Language :: Python :: 3.11
Requires-Python: >=3.8
Dynamic: author
Dynamic: home-page
Dynamic: requires-python
